django_admin_urls-0.3.1.dist-info/dependency_links.txt
django_admin_urls-0.3.1.dist-info/entry_points.txt
django_admin_urls-0.3.1.dist-info/METADATA
django_admin_urls-0.3.1.dist-info/top_level.txt
django_admin_urls-0.3.1.dist-info/WHEEL
dj_admin_urls/urls.py
dj_admin_urls/utils.py
dj_admin_urls/__init__.py
django_admin_urls-0.3.1.dist-info/LICENSE
django_admin_urls-0.3.1.dist-info/AUTHORS
django_admin_urls-0.3.1.dist-info/RECORD