Metadata-Version: 2.1
Name: django-admin-urls
Version: 0.3.1
Summary: Django admin url shortcuts
Project-URL: Repository, https://gitlab.com/cyberbudy/django-admin-urls/
Author: Alex Uzjakov
Author-email: cyberbudy@gmail.com
License: MIT
Requires-Python: >=3.6
Classifier: Development Status :: 4 - Beta
Classifier: Programming Language :: Python :: 3
Classifier: Framework :: Django
Classifier: Intended Audience :: Developers
Classifier: Topic :: Utilities
Classifier: License :: OSI Approved :: MIT License
Classifier: Operating System :: OS Independent
Requires-Dist: django>=3.0.0
